radiant/framework/__init__.py
radiant/framework/fake.py
radiant/framework/server.py
radiant/framework/utils.py
radiant/framework/static/brython/install_and_update.py
radiant/framework/static/brython/load_brython.js
radiant/framework/static/brython/Brython-3.10.7/README.txt
radiant/framework/static/brython/Brython-3.10.7/brython.js
radiant/framework/static/brython/Brython-3.10.7/brython_stdlib.js
radiant/framework/static/brython/Brython-3.10.7/demo.html
radiant/framework/static/brython/Brython-3.10.7/index.html
radiant/framework/static/brython/Brython-3.10.7/unicode.txt
radiant/framework/static/brython/Brython-3.11.3/README.txt
radiant/framework/static/brython/Brython-3.11.3/brython.js
radiant/framework/static/brython/Brython-3.11.3/brython_stdlib.js
radiant/framework/static/brython/Brython-3.11.3/demo.html
radiant/framework/static/brython/Brython-3.11.3/index.html
radiant/framework/static/brython/Brython-3.11.3/unicode.txt
radiant/framework/static/brython/Brython-3.12.5/README.txt
radiant/framework/static/brython/Brython-3.12.5/brython.js
radiant/framework/static/brython/Brython-3.12.5/brython_stdlib.js
radiant/framework/static/brython/Brython-3.12.5/demo.html
radiant/framework/static/brython/Brython-3.12.5/index.html
radiant/framework/static/brython/Brython-3.12.5/unicode.txt
radiant/framework/static/brython/Brython-3.13.0/README.txt
radiant/framework/static/brython/Brython-3.13.0/brython.js
radiant/framework/static/brython/Brython-3.13.0/brython_stdlib.js
radiant/framework/static/brython/Brython-3.13.0/demo.html
radiant/framework/static/brython/Brython-3.13.0/index.html
radiant/framework/static/brython/Brython-3.13.0/unicode.txt
radiant/framework/static/brython/Brython-3.13.1/README.txt
radiant/framework/static/brython/Brython-3.13.1/brython.js
radiant/framework/static/brython/Brython-3.13.1/brython_stdlib.js
radiant/framework/static/brython/Brython-3.13.1/demo.html
radiant/framework/static/brython/Brython-3.13.1/index.html
radiant_framework-0.3.1.dist-info/licenses/LICENSE.md
radiant_framework-0.3.1.dist-info/METADATA
radiant_framework-0.3.1.dist-info/WHEEL
radiant_framework-0.3.1.dist-info/top_level.txt
radiant_framework-0.3.1.dist-info/RECORD
