Metadata-Version: 2.4
Name: radiant-framework
Version: 0.3.1
Summary: Radiant Framework
Author-email: Yeison Cardona <yencardonaal@unal.edu.co>
Maintainer-email: Yeison Cardona <yencardonaal@unal.edu.co>
License: BSD-2-Clause
Project-URL: Download, https://github.com/dunderlab/python-radiant.framework
Classifier: Development Status :: 3 - Alpha
Classifier: License :: OSI Approved :: BSD License
Classifier: Programming Language :: Python :: 3.13
Classifier: Programming Language :: Python :: 3.12
Classifier: Programming Language :: Python :: 3.11
Classifier: Programming Language :: Python :: 3.10
Classifier: Programming Language :: Python :: 3.9
Classifier: Programming Language :: Python :: 3.8
Requires-Python: >=3.8
License-File: LICENSE.md
Requires-Dist: Jinja2
Requires-Dist: tornado
Requires-Dist: brython
Dynamic: license-file
